somlearn/__init__.py
somlearn/_version.py
somlearn/som.py
somlearn/tests/__init__.py
somlearn/tests/test_som.py
som_learn-0.1.1.dist-info/LICENSE
som_learn-0.1.1.dist-info/METADATA
som_learn-0.1.1.dist-info/WHEEL
som_learn-0.1.1.dist-info/top_level.txt
som_learn-0.1.1.dist-info/RECORD
