Metadata-Version: 2.1
Name: som-learn
Version: 0.1.1
Summary: Self-Organizing Map algorithm.
Home-page: https://github.com/AlgoWit/som-learn
Maintainer: G. Douzas
Maintainer-email: gdouzas@icloud.com
License: MIT
Download-URL: https://github.com/AlgoWit/som-learn
Platform: UNKNOWN
Classifier: Intended Audience :: Science/Research
Classifier: Intended Audience :: Developers
Classifier: License :: OSI Approved
Classifier: Programming Language :: Python
Classifier: Topic :: Software Development
Classifier: Topic :: Scientific/Engineering
Classifier: Operating System :: Microsoft :: Windows
Classifier: Operating System :: POSIX
Classifier: Operating System :: Unix
Classifier: Operating System :: MacOS
Classifier: Programming Language :: Python :: 3.6
Classifier: Programming Language :: Python :: 3.7
Requires-Dist: scipy (>=0.17)
Requires-Dist: numpy (>=1.1)
Requires-Dist: scikit-learn (>=0.21)
Requires-Dist: matplotlib (>=3.0)
Requires-Dist: somoclu (==1.7.5)
Provides-Extra: docs
Requires-Dist: sphinx (==1.8.5) ; extra == 'docs'
Requires-Dist: sphinx-gallery ; extra == 'docs'
Requires-Dist: sphinx-rtd-theme ; extra == 'docs'
Requires-Dist: numpydoc ; extra == 'docs'
Requires-Dist: matplotlib ; extra == 'docs'
Requires-Dist: pandas ; extra == 'docs'
Provides-Extra: tests
Requires-Dist: pytest ; extra == 'tests'
Requires-Dist: pytest-cov ; extra == 'tests'
